ccrf/__init__.py
ccrf/ccrf.py
ccrf/crf.py
ccrf/hidden_wfa.py
ccrf/multiple_crf.py
ccrf/patcrf.py
ccrf/utils.py
ccrf-0.0.3.dist-info/LICENSE
ccrf-0.0.3.dist-info/METADATA
ccrf-0.0.3.dist-info/WHEEL
ccrf-0.0.3.dist-info/top_level.txt
ccrf-0.0.3.dist-info/RECORD
